streaming_indicators/__init__.py
streaming_indicators/streaming_indicators.py
streaming_indicators-0.1.8.dist-info/licenses/LICENSE.txt
streaming_indicators-0.1.8.dist-info/METADATA
streaming_indicators-0.1.8.dist-info/WHEEL
streaming_indicators-0.1.8.dist-info/top_level.txt
streaming_indicators-0.1.8.dist-info/RECORD
