Metadata-Version: 2.4
Name: streaming_indicators
Version: 0.1.8
Summary: A python library for computing technical analysis indicators on streaming data.
Home-page: https://github.com/mr-easy/streaming_indicators
Author: Rishabh Gupta
Author-email: rishabhg1997@gmail.com
Project-URL: Bug Tracker, https://github.com/mr-easy/streaming_indicators/issues
Project-URL: Code, https://github.com/mr-easy/streaming_indicators
Classifier: Programming Language :: Python :: 3
Classifier: License :: OSI Approved :: MIT License
Classifier: Operating System :: OS Independent
Requires-Python: >=3.4
License-File: LICENSE.txt
Requires-Dist: numpy>=1.13.3
Requires-Dist: pandas>=2.0.0
Dynamic: license-file
